odoo/addons/stock_picking_volume_packaging/README.rst
odoo/addons/stock_picking_volume_packaging/__init__.py
odoo/addons/stock_picking_volume_packaging/__manifest__.py
odoo/addons/stock_picking_volume_packaging/i18n/stock_picking_volume_packaging.pot
odoo/addons/stock_picking_volume_packaging/models/__init__.py
odoo/addons/stock_picking_volume_packaging/models/product_product.py
odoo/addons/stock_picking_volume_packaging/readme/CONTRIBUTORS.rst
odoo/addons/stock_picking_volume_packaging/readme/CREDITS.rst
odoo/addons/stock_picking_volume_packaging/readme/DESCRIPTION.rst
odoo/addons/stock_picking_volume_packaging/readme/USAGE.rst
odoo/addons/stock_picking_volume_packaging/static/description/icon.png
odoo/addons/stock_picking_volume_packaging/static/description/index.html
odoo/addons/stock_picking_volume_packaging/tests/__init__.py
odoo/addons/stock_picking_volume_packaging/tests/test_stock_move_volume.py
odoo14_addon_stock_picking_volume_packaging-14.0.1.1.0.dist-info/METADATA
odoo14_addon_stock_picking_volume_packaging-14.0.1.1.0.dist-info/WHEEL
odoo14_addon_stock_picking_volume_packaging-14.0.1.1.0.dist-info/top_level.txt
odoo14_addon_stock_picking_volume_packaging-14.0.1.1.0.dist-info/RECORD
