Metadata-Version: 2.1
Name: odoo14-addon-stock-picking-volume-packaging
Version: 14.0.1.1.0
Summary: Use volume information on potential product packaging to compute the volume of a stock.move
Home-page: https://github.com/OCA/stock-logistics-warehouse
Author: ACSONE SA/NV,Odoo Community Association (OCA)
Author-email: support@odoo-community.org
License: AGPL-3
Platform: UNKNOWN
Classifier: Programming Language :: Python
Classifier: Framework :: Odoo
Classifier: Framework :: Odoo :: 14.0
Classifier: License :: OSI Approved :: GNU Affero General Public License v3
Requires-Python: >=3.6
Requires-Dist: odoo14-addon-product-packaging-dimension
Requires-Dist: odoo14-addon-stock-packaging-calculator
Requires-Dist: odoo14-addon-stock-picking-volume
Requires-Dist: odoo (<14.1dev,>=14.0a)
